aiko_services/__init__.py
aiko_services/elements/control/elements.py
aiko_services/elements/control/pipelines/factorial_pipeline.json
aiko_services/elements/gstreamer/__init__.py
aiko_services/elements/gstreamer/rtsp_io.py
aiko_services/elements/gstreamer/scheme_rtsp.py
aiko_services/elements/gstreamer/utilities.py
aiko_services/elements/gstreamer/video_camera_reader.py
aiko_services/elements/gstreamer/video_example.py
aiko_services/elements/gstreamer/video_file_reader.py
aiko_services/elements/gstreamer/video_file_writer.py
aiko_services/elements/gstreamer/video_reader.py
aiko_services/elements/gstreamer/video_stream_reader.py
aiko_services/elements/gstreamer/video_stream_writer.py
aiko_services/elements/gstreamer/pipelines/rtsp_pipeline_0.json
aiko_services/elements/gstreamer/pipelines/rtsp_pipeline_1.json
aiko_services/elements/media/__init__.py
aiko_services/elements/media/audio_io.py
aiko_services/elements/media/elements.py
aiko_services/elements/media/image_io.py
aiko_services/elements/media/images_to_video.py
aiko_services/elements/media/scheme_file.py
aiko_services/elements/media/scheme_tty.py
aiko_services/elements/media/scheme_zmq.py
aiko_services/elements/media/text_io.py
aiko_services/elements/media/video_example.py
aiko_services/elements/media/video_io.py
aiko_services/elements/media/webcam_io.py
aiko_services/elements/media/data_in/in_00.jpeg
aiko_services/elements/media/data_in/in_00.txt
aiko_services/elements/media/data_in/in_01.jpeg
aiko_services/elements/media/data_in/in_01.txt
aiko_services/elements/media/data_in/in_02.jpeg
aiko_services/elements/media/data_in/in_02.txt
aiko_services/elements/media/data_out/.gitkeep
aiko_services/elements/media/pipelines/image_pipeline_0.json
aiko_services/elements/media/pipelines/image_pipeline_1.json
aiko_services/elements/media/pipelines/image_zmq_pipeline_0.json
aiko_services/elements/media/pipelines/image_zmq_pipeline_1.json
aiko_services/elements/media/pipelines/images_to_video_pipeline.json
highlighter_sdk-2.6.37.dist-info/METADATA
highlighter_sdk-2.6.37.dist-info/WHEEL
highlighter_sdk-2.6.37.dist-info/entry_points.txt
highlighter_sdk-2.6.37.dist-info/licenses/LICENSE
highlighter_sdk-2.6.37.dist-info/RECORD
