Metadata-Version: 2.4
Name: highlighter-sdk
Version: 2.6.37
Summary: Package to interact with the Highlighter Perception System
Project-URL: Documentation, https://highlighter-docs.netlify.app/
Author-email: Joshua Patterson <joshua.patterson@silverpond.com.au>, Jono Chang <jonathan.chang@silverpond.com.au>, Simon Hudson <simon.hudson@silverpond.com.au>
License-File: LICENSE
Keywords: enterprise perception system
Classifier: Intended Audience :: Developers
Classifier: License :: OSI Approved :: Apache Software License
Classifier: Operating System :: Unix
Classifier: Programming Language :: Python :: 3.12
Classifier: Programming Language :: Python :: 3.13
Requires-Python: <=3.14,>=3.12
Requires-Dist: alembic==1.15.2
Requires-Dist: asciimatics~=1.15.0
Requires-Dist: avro-validator~=1.2.1
Requires-Dist: avro~=1.12.0
Requires-Dist: av~=14.1.0
Requires-Dist: boto3~=1.34.00
Requires-Dist: cel-python~=0.4.0
Requires-Dist: click!=8.0.0,<9,>=7
Requires-Dist: colorama~=0.4.4
Requires-Dist: cookiecutter
Requires-Dist: fastavro~=1.8
Requires-Dist: gql[aiohttp,requests]~=3.5.0
Requires-Dist: litellm~=1.80.0
Requires-Dist: paho-mqtt<2.0.0,>=1.6.1
Requires-Dist: pandas~=2.2
Requires-Dist: pillow~=10.4.0
Requires-Dist: pooch~=1.5
Requires-Dist: psutil~=6.0.0
Requires-Dist: pybreaker~=1.4.0
Requires-Dist: pydantic<2.9,>=1.6
Requires-Dist: pyperclip~=1.9.0
Requires-Dist: python-magic-bin~=0.4.0; sys_platform == 'win32'
Requires-Dist: python-magic~=0.4.0; sys_platform == 'darwin'
Requires-Dist: python-magic~=0.4.0; sys_platform == 'linux'
Requires-Dist: pyyaml>=5.0
Requires-Dist: pyzmq~=26.2.0
Requires-Dist: requests<3,>=2.32.3
Requires-Dist: scipy~=1.16.0
Requires-Dist: shapely>2.0.1
Requires-Dist: sqlmodel~=0.0.22
Requires-Dist: tenacity~=9.1.2
Requires-Dist: tomli-w~=1.2.0
Requires-Dist: tqdm~=4.0
Requires-Dist: transitions~=0.9.2
Requires-Dist: wrapt~=1.16.0
Requires-Dist: zeroconf<1.0.0,>=0.147.0
Provides-Extra: cv2
Requires-Dist: opencv-python~=4.7; extra == 'cv2'
Provides-Extra: hdf
Requires-Dist: tables~=3.7; extra == 'hdf'
Provides-Extra: matplotlib
Requires-Dist: matplotlib~=3.10; extra == 'matplotlib'
Provides-Extra: predictors
Requires-Dist: onnxruntime; extra == 'predictors'
Requires-Dist: opencv-python~=4.7; extra == 'predictors'
Requires-Dist: torch; extra == 'predictors'
Provides-Extra: rtspserver
Requires-Dist: pygobject; extra == 'rtspserver'
Provides-Extra: tracker
Requires-Dist: pykalman~=0.10.1; extra == 'tracker'
Requires-Dist: torch; extra == 'tracker'
Provides-Extra: yolo
Requires-Dist: onnx; extra == 'yolo'
Requires-Dist: onnxruntime; extra == 'yolo'
Requires-Dist: opencv-python~=4.7; extra == 'yolo'
Requires-Dist: torch; extra == 'yolo'
Requires-Dist: ultralytics; extra == 'yolo'
